qcompute_qep/__init__.py
qcompute_qep/benchmarking/__init__.py
qcompute_qep/benchmarking/benchmarking.py
qcompute_qep/benchmarking/interleavedrb.py
qcompute_qep/benchmarking/standardrb.py
qcompute_qep/benchmarking/unitarityrb.py
qcompute_qep/benchmarking/xeb.py
qcompute_qep/correction/__init__.py
qcompute_qep/correction/basic.py
qcompute_qep/correction/stabilizer.py
qcompute_qep/correction/utils.py
qcompute_qep/estimation/__init__.py
qcompute_qep/estimation/cpe_process.py
qcompute_qep/estimation/cpe_state.py
qcompute_qep/estimation/dfe_process.py
qcompute_qep/estimation/dfe_state.py
qcompute_qep/estimation/estimation.py
qcompute_qep/exceptions/QEPError.py
qcompute_qep/exceptions/__init__.py
qcompute_qep/interface/__init__.py
qcompute_qep/interface/conversion.py
qcompute_qep/measurement/__init__.py
qcompute_qep/measurement/calibration.py
qcompute_qep/measurement/correction.py
qcompute_qep/measurement/utils.py
qcompute_qep/mitigation/__init__.py
qcompute_qep/mitigation/mitigation.py
qcompute_qep/mitigation/utils.py
qcompute_qep/mitigation/zne/__init__.py
qcompute_qep/mitigation/zne/extrapolator.py
qcompute_qep/mitigation/zne/folder.py
qcompute_qep/mitigation/zne/zne.py
qcompute_qep/quantum/__init__.py
qcompute_qep/quantum/channel.py
qcompute_qep/quantum/clifford.py
qcompute_qep/quantum/entropies.py
qcompute_qep/quantum/gellmann.py
qcompute_qep/quantum/metrics.py
qcompute_qep/quantum/pauli.py
qcompute_qep/tomography/__init__.py
qcompute_qep/tomography/basis.py
qcompute_qep/tomography/detector_tomography.py
qcompute_qep/tomography/gateset.py
qcompute_qep/tomography/gateset_optimizer.py
qcompute_qep/tomography/gateset_tomography.py
qcompute_qep/tomography/process_tomography.py
qcompute_qep/tomography/spectral_tomography.py
qcompute_qep/tomography/state_tomography.py
qcompute_qep/tomography/tomography.py
qcompute_qep/tomography/utils.py
qcompute_qep/utils/MultiCtrlGates.py
qcompute_qep/utils/__init__.py
qcompute_qep/utils/circuit.py
qcompute_qep/utils/gate.py
qcompute_qep-1.1.0.dist-info/LICENSE
qcompute_qep-1.1.0.dist-info/METADATA
qcompute_qep-1.1.0.dist-info/WHEEL
qcompute_qep-1.1.0.dist-info/top_level.txt
qcompute_qep-1.1.0.dist-info/RECORD
