Metadata-Version: 2.1
Name: qcompute-qep
Version: 1.1.0
Summary: A Quantum Error Processing toolkit developed by the Institute for Quantum Computing at Baidu Research.
Home-page: https://quantum-hub.baidu.com/qep/
Author: Baidu Quantum
Author-email: quantum@baidu.com
License: Apache 2.0
Classifier: Programming Language :: Python :: 3
Classifier: License :: OSI Approved :: Apache Software License
Classifier: Operating System :: OS Independent
Requires-Python: >=3.8
License-File: LICENSE
Requires-Dist: matplotlib (>=3.5.2)
Requires-Dist: networkx (>=2.8.3)
Requires-Dist: numpy (>=1.21.3)
Requires-Dist: pandas (>=1.4.2)
Requires-Dist: qcompute (>=3.3.0)
Requires-Dist: qiskit (>=0.37.0)
Requires-Dist: qiskit-ibmq-provider (>=0.19.2)
Requires-Dist: scipy (>=1.7.1)
Requires-Dist: seaborn (>=0.11.2)
Requires-Dist: tqdm (>=4.64.0)
Requires-Dist: qutip (>=4.7.0)
